inpout/__init__.py
inpout/cli.py
inpout/compression.py
inpout/ext_types.py
inpout/inpout.py
inpout/packing.py
inpout-1.0.8.dist-info/LICENSE
inpout-1.0.8.dist-info/METADATA
inpout-1.0.8.dist-info/WHEEL
inpout-1.0.8.dist-info/entry_points.txt
inpout-1.0.8.dist-info/top_level.txt
inpout-1.0.8.dist-info/RECORD
