Metadata-Version: 2.1
Name: inpout
Version: 1.0.8
Summary: Simple input/output using MessagePack and LZ4 for Python
Home-page: https://github.com/hhromic/python-inpout
Author: Hugo Hromic
Author-email: hhromic@gmail.com
Maintainer: Hugo Hromic
Maintainer-email: hhromic@gmail.com
License: Apache-2.0
Download-URL: https://github.com/hhromic/python-inpout/tarball/1.0.8
Keywords: messagepack,lz4,input,output,library
Platform: all
Classifier: Topic :: System :: Archiving
Classifier: Intended Audience :: Developers
Provides: inpout
Requires-Dist: msgpack
Requires-Dist: py-lz4framed
